kosha/__init__.py
kosha/metadata.py
pykosha-0.0.1.dist-info/METADATA
pykosha-0.0.1.dist-info/WHEEL
pykosha-0.0.1.dist-info/entry_points.txt
pykosha-0.0.1.dist-info/RECORD
