Metadata-Version: 2.4
Name: pykosha
Version: 0.0.1
Summary: A workflow description language
Project-URL: Source, https://github.com/orgkosha/pykosha
Author-email: Jayesh Badwaik <jayesh@ambhora.com>
License-Expression: Apache-2.0
Requires-Dist: livereload
Requires-Dist: semver
